MANIFEST.in
README.md
requirements.txt
setup.cfg
setup.py
plasso/PliableLasso.py
plasso/__init__.py
plasso/numbaSolver.py
plasso/packageInfo.py
plasso/torchSolver.py
plasso.egg-info/PKG-INFO
plasso.egg-info/SOURCES.txt
plasso.egg-info/dependency_links.txt
plasso.egg-info/not-zip-safe
plasso.egg-info/requires.txt
plasso.egg-info/top_level.txt