Metadata-Version: 1.1
Name: plasso
Version: 1.20190329.1200
Summary: Pliable Lasso
Home-page: https://github.com/arose13/PliableLasso
Author: Stephen Rose
Author-email: me@stephenro.se
License: BSD
Platform: UNKNOWN
Classifier: Development Status :: 4 - Beta
Classifier: Intended Audience :: Developers
Classifier: Programming Language :: Python :: 3
Classifier: Topic :: Scientific/Engineering :: Artificial Intelligence
